alltime_athletics_python/__init__.py
alltime_athletics_python/app.py
alltime_athletics_python/events.py
alltime_athletics_python/get_content.py
alltime_athletics_python/get_content_urls.py
alltime_athletics_python/io.py
alltime_athletics_python/pipes.py
alltime_athletics_python/utils/__init__.py
alltime_athletics_python/utils/config.py
alltime_athletics_python/utils/logger.py
alltime_athletics_python-1.20241023.1.dist-info/LICENSE
alltime_athletics_python-1.20241023.1.dist-info/METADATA
alltime_athletics_python-1.20241023.1.dist-info/WHEEL
alltime_athletics_python-1.20241023.1.dist-info/RECORD
