Metadata-Version: 2.1
Name: alltime_athletics_python
Version: 1.20241023.1
Summary: Scrapes and post-processes data from Alltime Athletics (website by Peter Larsson)
Home-page: https://github.com/thomascamminady/alltime_athletics_python
Author: Thomas Camminady
Author-email: 0milieux_member@icloud.com
Requires-Python: >=3.10,<4.0
Classifier: Programming Language :: Python :: 3
Classifier: Programming Language :: Python :: 3.10
Classifier: Programming Language :: Python :: 3.11
Classifier: Programming Language :: Python :: 3.12
Requires-Dist: html5lib (>=1.1,<2.0)
Requires-Dist: ipywidgets (>=8.0.6,<9.0.0)
Requires-Dist: lxml (>=4.9.2,<5.0.0)
Requires-Dist: pandas (>=2.2.2,<3.0.0)
Requires-Dist: polars (>=1.1.0,<2.0.0)
Requires-Dist: pyarrow (>=16.1.0,<17.0.0)
Requires-Dist: rich (>=13.4.1,<14.0.0)
Requires-Dist: tabulate (>=0.9.0,<0.10.0)
